setlogging/__init__.py
setlogging/logger.py
setlogging-0.4.3.dist-info/METADATA
setlogging-0.4.3.dist-info/WHEEL
setlogging-0.4.3.dist-info/licenses/LICENSE
setlogging-0.4.3.dist-info/RECORD
