Metadata-Version: 2.4
Name: setlogging
Version: 0.4.3
Summary: A flexible logging utility with JSON support and timezone awareness
Project-URL: Homepage, https://github.com/JieYanTIBCO/setlogging
Project-URL: Repository, https://github.com/JieYanTIBCO/setlogging
Author-email: Jie Yan <kiki3890528@gmail.com>
License: MIT
License-File: LICENSE
Keywords: json,logging,timezone
Classifier: License :: OSI Approved :: MIT License
Classifier: Operating System :: OS Independent
Classifier: Programming Language :: Python :: 3
Requires-Python: >=3.9
